[
  {
    "chapter": 34,
    "segments": [
      [
        0,
        1,
        1150,
        2050
      ],
      [
        1,
        2,
        2060,
        3220
      ],
      [
        2,
        3,
        3230,
        3860
      ],
      [
        3,
        4,
        3870,
        4490
      ],
      [
        4,
        5,
        4500,
        5080
      ],
      [
        5,
        6,
        5090,
        5330
      ],
      [
        6,
        7,
        5340,
        6630
      ],
      [
        7,
        8,
        6640,
        7220
      ],
      [
        8,
        9,
        7230,
        7430
      ],
      [
        9,
        10,
        7440,
        8290
      ],
      [
        10,
        11,
        8300,
        9090
      ],
      [
        11,
        12,
        9100,
        9900
      ],
      [
        12,
        13,
        9910,
        10130
      ],
      [
        13,
        14,
        10140,
        11480
      ],
      [
        14,
        15,
        11490,
        12060
      ],
      [
        15,
        16,
        12070,
        13120
      ],
      [
        16,
        17,
        13130,
        14880
      ]
    ],
    "url": "Rifai/mp3/034001.mp3",
    "verse": 1
  },
  {
    "chapter": 34,
    "segments": [
      [
        0,
        1,
        40,
        860
      ],
      [
        1,
        2,
        870,
        1250
      ],
      [
        2,
        3,
        1260,
        1740
      ],
      [
        3,
        4,
        1750,
        1980
      ],
      [
        4,
        5,
        1990,
        2720
      ],
      [
        5,
        6,
        2730,
        3250
      ],
      [
        6,
        7,
        3260,
        4170
      ],
      [
        7,
        8,
        4180,
        4990
      ],
      [
        8,
        9,
        5000,
        5820
      ],
      [
        9,
        10,
        5830,
        6810
      ],
      [
        10,
        11,
        6820,
        7200
      ],
      [
        11,
        12,
        7210,
        9080
      ],
      [
        12,
        13,
        9090,
        9620
      ],
      [
        13,
        14,
        9630,
        10440
      ],
      [
        14,
        15,
        10450,
        11410
      ],
      [
        15,
        16,
        11420,
        12240
      ],
      [
        16,
        17,
        12250,
        13230
      ],
      [
        17,
        18,
        13240,
        14690
      ]
    ],
    "url": "Rifai/mp3/034002.mp3",
    "verse": 2
  },
  {
    "chapter": 34,
    "segments": [
      [
        0,
        1,
        100,
        840
      ],
      [
        1,
        2,
        850,
        1880
      ],
      [
        2,
        3,
        1890,
        2730
      ],
      [
        3,
        4,
        2740,
        3090
      ],
      [
        4,
        5,
        3100,
        4160
      ],
      [
        5,
        6,
        4170,
        5500
      ],
      [
        6,
        7,
        5510,
        5830
      ],
      [
        7,
        8,
        5840,
        6540
      ],
      [
        8,
        9,
        6550,
        7400
      ],
      [
        9,
        10,
        7410,
        9920
      ],
      [
        10,
        11,
        9930,
        10730
      ],
      [
        11,
        12,
        10740,
        12280
      ],
      [
        12,
        13,
        12290,
        12690
      ],
      [
        13,
        14,
        12700,
        13400
      ],
      [
        14,
        15,
        13410,
        14060
      ],
      [
        15,
        16,
        14070,
        14960
      ],
      [
        16,
        17,
        14970,
        16270
      ],
      [
        17,
        18,
        16280,
        16460
      ],
      [
        18,
        19,
        16470,
        17840
      ],
      [
        19,
        20,
        17850,
        18430
      ],
      [
        20,
        21,
        18440,
        18640
      ],
      [
        21,
        22,
        18650,
        19700
      ],
      [
        22,
        23,
        19710,
        20330
      ],
      [
        23,
        24,
        20340,
        21160
      ],
      [
        24,
        25,
        21170,
        21720
      ],
      [
        25,
        26,
        21730,
        22600
      ],
      [
        26,
        27,
        22610,
        23130
      ],
      [
        27,
        28,
        23140,
        23910
      ],
      [
        28,
        29,
        23920,
        24590
      ],
      [
        29,
        30,
        24600,
        24980
      ],
      [
        30,
        31,
        24990,
        26240
      ],
      [
        31,
        32,
        26250,
        27970
      ]
    ],
    "url": "Rifai/mp3/034003.mp3",
    "verse": 3
  },
  {
    "chapter": 34,
    "segments": [
      [
        0,
        1,
        160,
        1110
      ],
      [
        1,
        2,
        1120,
        2090
      ],
      [
        2,
        3,
        2100,
        3080
      ],
      [
        3,
        4,
        3090,
        3850
      ],
      [
        4,
        5,
        3860,
        6000
      ],
      [
        5,
        6,
        6010,
        7920
      ],
      [
        6,
        7,
        7930,
        8330
      ],
      [
        7,
        8,
        8340,
        9730
      ],
      [
        8,
        9,
        9740,
        12020
      ],
      [
        9,
        10,
        12030,
        13240
      ]
    ],
    "url": "Rifai/mp3/034004.mp3",
    "verse": 4
  },
  {
    "chapter": 34,
    "segments": [
      [
        0,
        1,
        170,
        1260
      ],
      [
        1,
        2,
        1270,
        1890
      ],
      [
        2,
        3,
        1900,
        2690
      ],
      [
        3,
        4,
        2700,
        3700
      ],
      [
        4,
        5,
        3710,
        5730
      ],
      [
        5,
        6,
        5740,
        7330
      ],
      [
        6,
        7,
        7340,
        7820
      ],
      [
        7,
        8,
        7830,
        9310
      ],
      [
        8,
        9,
        9320,
        9390
      ],
      [
        9,
        10,
        9400,
        10330
      ],
      [
        10,
        11,
        10340,
        11880
      ]
    ],
    "url": "Rifai/mp3/034005.mp3",
    "verse": 5
  },
  {
    "chapter": 34,
    "segments": [
      [
        0,
        1,
        190,
        740
      ],
      [
        1,
        2,
        750,
        1730
      ],
      [
        2,
        3,
        1740,
        2290
      ],
      [
        3,
        4,
        2300,
        3040
      ],
      [
        4,
        5,
        3050,
        3870
      ],
      [
        5,
        6,
        3880,
        4840
      ],
      [
        6,
        7,
        4850,
        5700
      ],
      [
        7,
        8,
        5710,
        5810
      ],
      [
        8,
        9,
        5820,
        6910
      ],
      [
        9,
        10,
        6920,
        7270
      ],
      [
        10,
        11,
        7280,
        8090
      ],
      [
        11,
        12,
        8100,
        9680
      ],
      [
        12,
        13,
        9690,
        10150
      ],
      [
        13,
        14,
        10160,
        11030
      ],
      [
        14,
        15,
        11040,
        12100
      ],
      [
        15,
        16,
        12110,
        13720
      ]
    ],
    "url": "Rifai/mp3/034006.mp3",
    "verse": 6
  },
  {
    "chapter": 34,
    "segments": [
      [
        0,
        1,
        170,
        980
      ],
      [
        1,
        2,
        990,
        1990
      ],
      [
        2,
        3,
        2000,
        2870
      ],
      [
        3,
        4,
        2880,
        3290
      ],
      [
        4,
        5,
        3300,
        4470
      ],
      [
        5,
        6,
        4480,
        5090
      ],
      [
        6,
        7,
        5100,
        6100
      ],
      [
        7,
        8,
        6110,
        7470
      ],
      [
        8,
        9,
        7480,
        8210
      ],
      [
        9,
        10,
        8220,
        9410
      ],
      [
        10,
        11,
        9420,
        10110
      ],
      [
        11,
        12,
        10120,
        11450
      ],
      [
        12,
        13,
        11460,
        13500
      ],
      [
        13,
        14,
        15410,
        15960
      ],
      [
        14,
        15,
        15970,
        17410
      ],
      [
        15,
        16,
        17420,
        19190
      ]
    ],
    "url": "Rifai/mp3/034007.mp3",
    "verse": 7
  },
  {
    "chapter": 34,
    "segments": [
      [
        0,
        1,
        30,
        990
      ],
      [
        1,
        2,
        1000,
        1560
      ],
      [
        2,
        3,
        1570,
        2150
      ],
      [
        3,
        4,
        2160,
        3610
      ],
      [
        4,
        5,
        3620,
        4280
      ],
      [
        5,
        6,
        4290,
        4970
      ],
      [
        6,
        7,
        4980,
        6490
      ],
      [
        7,
        8,
        6500,
        6800
      ],
      [
        8,
        9,
        6810,
        7790
      ],
      [
        9,
        10,
        7800,
        8210
      ],
      [
        10,
        11,
        8220,
        9270
      ],
      [
        11,
        12,
        9280,
        10690
      ],
      [
        12,
        13,
        10700,
        10870
      ],
      [
        13,
        14,
        10880,
        11920
      ],
      [
        14,
        15,
        11930,
        13070
      ],
      [
        15,
        16,
        13080,
        14890
      ]
    ],
    "url": "Rifai/mp3/034008.mp3",
    "verse": 8
  },
  {
    "chapter": 34,
    "segments": [
      [
        0,
        1,
        140,
        930
      ],
      [
        1,
        2,
        940,
        1530
      ],
      [
        2,
        3,
        1540,
        2090
      ],
      [
        3,
        4,
        2100,
        2490
      ],
      [
        4,
        5,
        2500,
        3010
      ],
      [
        5,
        6,
        3020,
        4310
      ],
      [
        6,
        7,
        4320,
        4870
      ],
      [
        7,
        8,
        4880,
        6280
      ],
      [
        8,
        9,
        6290,
        6560
      ],
      [
        9,
        10,
        6570,
        8940
      ],
      [
        10,
        11,
        8950,
        10220
      ],
      [
        11,
        12,
        10230,
        10290
      ],
      [
        12,
        13,
        10300,
        11670
      ],
      [
        13,
        14,
        11680,
        12500
      ],
      [
        14,
        15,
        12510,
        13180
      ],
      [
        15,
        16,
        13190,
        13990
      ],
      [
        16,
        17,
        14000,
        14380
      ],
      [
        17,
        18,
        14390,
        15170
      ],
      [
        18,
        19,
        15180,
        16130
      ],
      [
        19,
        20,
        16140,
        16950
      ],
      [
        20,
        21,
        16960,
        17740
      ],
      [
        21,
        22,
        17750,
        20260
      ],
      [
        22,
        23,
        20270,
        21370
      ],
      [
        23,
        24,
        21380,
        21760
      ],
      [
        24,
        25,
        21770,
        22650
      ],
      [
        25,
        26,
        22660,
        23910
      ],
      [
        26,
        27,
        23920,
        24690
      ],
      [
        27,
        28,
        24700,
        26220
      ],
      [
        28,
        29,
        26230,
        28170
      ]
    ],
    "url": "Rifai/mp3/034009.mp3",
    "verse": 9
  },
  {
    "chapter": 34,
    "segments": [
      [
        0,
        1,
        500,
        1210
      ],
      [
        1,
        2,
        1220,
        2480
      ],
      [
        2,
        3,
        2490,
        3510
      ],
      [
        3,
        4,
        3520,
        4660
      ],
      [
        4,
        5,
        4670,
        5970
      ],
      [
        5,
        6,
        5980,
        7230
      ],
      [
        6,
        7,
        7240,
        8300
      ],
      [
        7,
        8,
        8310,
        9020
      ],
      [
        8,
        9,
        9030,
        15640
      ],
      [
        9,
        10,
        15650,
        17450
      ],
      [
        10,
        11,
        17460,
        17830
      ],
      [
        11,
        12,
        17840,
        19630
      ]
    ],
    "url": "Rifai/mp3/034010.mp3",
    "verse": 10
  }
]
