[
  {
    "chapter": 69,
    "segments": [
      [
        0,
        1,
        950,
        4060
      ]
    ],
    "url": "Rifai/mp3/069001.mp3",
    "verse": 1
  },
  {
    "chapter": 69,
    "segments": [
      [
        0,
        1,
        140,
        280
      ],
      [
        1,
        2,
        290,
        3540
      ]
    ],
    "url": "Rifai/mp3/069002.mp3",
    "verse": 2
  },
  {
    "chapter": 69,
    "segments": [
      [
        0,
        1,
        70,
        730
      ],
      [
        1,
        2,
        740,
        1770
      ],
      [
        2,
        3,
        1780,
        1960
      ],
      [
        3,
        4,
        1970,
        4880
      ]
    ],
    "url": "Rifai/mp3/069003.mp3",
    "verse": 3
  },
  {
    "chapter": 69,
    "segments": [
      [
        0,
        1,
        30,
        940
      ],
      [
        1,
        2,
        950,
        1870
      ],
      [
        2,
        3,
        1880,
        3100
      ],
      [
        3,
        4,
        3110,
        4440
      ]
    ],
    "url": "Rifai/mp3/069004.mp3",
    "verse": 4
  },
  {
    "chapter": 69,
    "segments": [
      [
        0,
        1,
        30,
        1090
      ],
      [
        1,
        2,
        1100,
        1900
      ],
      [
        2,
        3,
        1910,
        3120
      ],
      [
        3,
        4,
        3130,
        4630
      ]
    ],
    "url": "Rifai/mp3/069005.mp3",
    "verse": 5
  },
  {
    "chapter": 69,
    "segments": [
      [
        0,
        1,
        70,
        1310
      ],
      [
        1,
        2,
        1320,
        2420
      ],
      [
        2,
        3,
        2430,
        3660
      ],
      [
        3,
        4,
        3670,
        4890
      ],
      [
        4,
        5,
        4900,
        5930
      ],
      [
        5,
        6,
        5940,
        6970
      ]
    ],
    "url": "Rifai/mp3/069006.mp3",
    "verse": 6
  },
  {
    "chapter": 69,
    "segments": [
      [
        0,
        1,
        120,
        1220
      ],
      [
        1,
        2,
        1230,
        2200
      ],
      [
        2,
        3,
        2210,
        2840
      ],
      [
        3,
        4,
        2850,
        3630
      ],
      [
        4,
        5,
        3640,
        5940
      ],
      [
        5,
        6,
        5950,
        6730
      ],
      [
        6,
        7,
        6740,
        8040
      ],
      [
        7,
        8,
        8050,
        8620
      ],
      [
        8,
        9,
        8630,
        9420
      ],
      [
        9,
        10,
        9430,
        10230
      ],
      [
        10,
        11,
        10240,
        11510
      ],
      [
        11,
        12,
        11520,
        13110
      ],
      [
        12,
        13,
        13120,
        14140
      ],
      [
        13,
        14,
        14150,
        14900
      ],
      [
        14,
        15,
        14910,
        15870
      ]
    ],
    "url": "Rifai/mp3/069007.mp3",
    "verse": 7
  },
  {
    "chapter": 69,
    "segments": [
      [
        0,
        1,
        50,
        560
      ],
      [
        1,
        2,
        570,
        1270
      ],
      [
        2,
        3,
        1280,
        1930
      ],
      [
        3,
        4,
        1940,
        2960
      ],
      [
        4,
        5,
        2970,
        4080
      ]
    ],
    "url": "Rifai/mp3/069008.mp3",
    "verse": 8
  },
  {
    "chapter": 69,
    "segments": [
      [
        0,
        1,
        150,
        1500
      ],
      [
        1,
        2,
        1510,
        2580
      ],
      [
        2,
        3,
        2590,
        3540
      ],
      [
        3,
        4,
        3550,
        4550
      ],
      [
        4,
        5,
        4560,
        6440
      ],
      [
        5,
        6,
        6450,
        7960
      ]
    ],
    "url": "Rifai/mp3/069009.mp3",
    "verse": 9
  },
  {
    "chapter": 69,
    "segments": [
      [
        0,
        1,
        90,
        950
      ],
      [
        1,
        2,
        960,
        1790
      ],
      [
        2,
        3,
        1800,
        3250
      ],
      [
        3,
        4,
        3260,
        4490
      ],
      [
        4,
        5,
        4500,
        5380
      ],
      [
        5,
        6,
        5390,
        6660
      ]
    ],
    "url": "Rifai/mp3/069010.mp3",
    "verse": 10
  }
]
