[
  {
    "chapter": 25,
    "segments": [
      [
        0,
        1,
        40,
        690
      ],
      [
        1,
        2,
        700,
        1270
      ],
      [
        2,
        3,
        1280,
        1810
      ],
      [
        3,
        4,
        1820,
        2660
      ],
      [
        4,
        5,
        2670,
        3040
      ],
      [
        5,
        6,
        3050,
        3840
      ],
      [
        6,
        7,
        3850,
        4540
      ],
      [
        7,
        8,
        4550,
        5580
      ],
      [
        8,
        9,
        5590,
        6360
      ]
    ],
    "url": "Shuraym/mp3/025001.mp3",
    "verse": 1
  },
  {
    "chapter": 25,
    "segments": [
      [
        0,
        1,
        100,
        720
      ],
      [
        1,
        2,
        730,
        1180
      ],
      [
        2,
        3,
        1190,
        1560
      ],
      [
        3,
        4,
        1570,
        2640
      ],
      [
        4,
        5,
        2650,
        3340
      ],
      [
        5,
        6,
        3350,
        3700
      ],
      [
        6,
        7,
        3710,
        4360
      ],
      [
        7,
        8,
        4370,
        5180
      ],
      [
        8,
        9,
        5190,
        5510
      ],
      [
        9,
        10,
        5520,
        5930
      ],
      [
        10,
        11,
        5940,
        6340
      ],
      [
        11,
        12,
        6350,
        7340
      ],
      [
        12,
        13,
        7350,
        7510
      ],
      [
        13,
        14,
        7520,
        8450
      ],
      [
        14,
        15,
        8460,
        9120
      ],
      [
        15,
        16,
        9130,
        9570
      ],
      [
        16,
        17,
        9580,
        10770
      ],
      [
        17,
        18,
        10780,
        11850
      ],
      [
        18,
        19,
        11860,
        12930
      ]
    ],
    "url": "Shuraym/mp3/025002.mp3",
    "verse": 2
  },
  {
    "chapter": 25,
    "segments": [
      [
        0,
        1,
        30,
        810
      ],
      [
        1,
        2,
        820,
        1360
      ],
      [
        2,
        3,
        1370,
        2050
      ],
      [
        3,
        4,
        2060,
        2840
      ],
      [
        4,
        5,
        2850,
        3140
      ],
      [
        5,
        6,
        3150,
        3980
      ],
      [
        6,
        7,
        3990,
        4390
      ],
      [
        7,
        8,
        4400,
        5220
      ],
      [
        8,
        9,
        5230,
        6750
      ],
      [
        9,
        10,
        6760,
        7100
      ],
      [
        10,
        11,
        7110,
        7940
      ],
      [
        11,
        12,
        7950,
        9150
      ],
      [
        12,
        13,
        9160,
        9630
      ],
      [
        13,
        14,
        9640,
        10330
      ],
      [
        14,
        15,
        10340,
        11310
      ],
      [
        15,
        16,
        11320,
        11700
      ],
      [
        16,
        17,
        11710,
        12520
      ],
      [
        17,
        18,
        12530,
        13260
      ],
      [
        18,
        19,
        13270,
        13680
      ],
      [
        19,
        20,
        13690,
        14620
      ],
      [
        20,
        21,
        14630,
        15020
      ],
      [
        21,
        22,
        15030,
        15900
      ]
    ],
    "url": "Shuraym/mp3/025003.mp3",
    "verse": 3
  },
  {
    "chapter": 25,
    "segments": [
      [
        0,
        1,
        50,
        510
      ],
      [
        1,
        2,
        520,
        1220
      ],
      [
        2,
        3,
        1230,
        1880
      ],
      [
        3,
        4,
        1890,
        2100
      ],
      [
        4,
        5,
        2110,
        2430
      ],
      [
        5,
        6,
        2440,
        3080
      ],
      [
        6,
        7,
        3090,
        3720
      ],
      [
        7,
        8,
        3730,
        4430
      ],
      [
        8,
        9,
        4440,
        5350
      ],
      [
        9,
        10,
        5360,
        5930
      ],
      [
        10,
        11,
        5940,
        6520
      ],
      [
        11,
        12,
        6530,
        7860
      ],
      [
        12,
        13,
        7870,
        8320
      ],
      [
        13,
        14,
        8330,
        9830
      ],
      [
        14,
        15,
        9840,
        10210
      ],
      [
        15,
        16,
        10220,
        11410
      ]
    ],
    "url": "Shuraym/mp3/025004.mp3",
    "verse": 4
  },
  {
    "chapter": 25,
    "segments": [
      [
        0,
        1,
        70,
        980
      ],
      [
        1,
        2,
        990,
        1600
      ],
      [
        2,
        3,
        1610,
        2600
      ],
      [
        3,
        4,
        2610,
        3420
      ],
      [
        4,
        5,
        3430,
        3890
      ],
      [
        5,
        6,
        3900,
        4420
      ],
      [
        6,
        7,
        4430,
        5060
      ],
      [
        7,
        8,
        5070,
        6060
      ],
      [
        8,
        9,
        6070,
        6880
      ]
    ],
    "url": "Shuraym/mp3/025005.mp3",
    "verse": 5
  },
  {
    "chapter": 25,
    "segments": [
      [
        0,
        1,
        70,
        330
      ],
      [
        1,
        2,
        340,
        1380
      ],
      [
        2,
        3,
        1390,
        1910
      ],
      [
        3,
        4,
        1920,
        2440
      ],
      [
        4,
        5,
        2450,
        2960
      ],
      [
        5,
        6,
        2970,
        3120
      ],
      [
        6,
        7,
        3130,
        4200
      ],
      [
        7,
        8,
        4210,
        4840
      ],
      [
        8,
        9,
        4850,
        5960
      ],
      [
        9,
        10,
        5970,
        6480
      ],
      [
        10,
        11,
        6490,
        7060
      ],
      [
        11,
        12,
        7070,
        7820
      ]
    ],
    "url": "Shuraym/mp3/025006.mp3",
    "verse": 6
  },
  {
    "chapter": 25,
    "segments": [
      [
        0,
        1,
        60,
        770
      ],
      [
        1,
        2,
        780,
        1180
      ],
      [
        2,
        3,
        1190,
        1620
      ],
      [
        3,
        4,
        1630,
        2300
      ],
      [
        4,
        5,
        2310,
        2830
      ],
      [
        5,
        6,
        2840,
        3550
      ],
      [
        6,
        7,
        3560,
        4280
      ],
      [
        7,
        8,
        4290,
        4430
      ],
      [
        8,
        9,
        4440,
        6920
      ],
      [
        9,
        10,
        6930,
        7480
      ],
      [
        10,
        11,
        7490,
        8370
      ],
      [
        11,
        12,
        8380,
        8930
      ],
      [
        12,
        13,
        8940,
        9750
      ],
      [
        13,
        14,
        9760,
        10550
      ],
      [
        14,
        15,
        10560,
        11150
      ],
      [
        15,
        16,
        11160,
        11970
      ]
    ],
    "url": "Shuraym/mp3/025007.mp3",
    "verse": 7
  },
  {
    "chapter": 25,
    "segments": [
      [
        0,
        1,
        70,
        260
      ],
      [
        1,
        2,
        270,
        680
      ],
      [
        2,
        3,
        690,
        1440
      ],
      [
        3,
        4,
        1450,
        2420
      ],
      [
        4,
        5,
        2430,
        2660
      ],
      [
        5,
        6,
        2670,
        3280
      ],
      [
        6,
        7,
        3290,
        3680
      ],
      [
        7,
        8,
        3690,
        5120
      ],
      [
        8,
        9,
        5130,
        5760
      ],
      [
        9,
        10,
        5770,
        6840
      ],
      [
        10,
        11,
        6850,
        7430
      ],
      [
        11,
        12,
        7440,
        8490
      ],
      [
        12,
        13,
        8500,
        9110
      ],
      [
        13,
        14,
        9120,
        10090
      ],
      [
        14,
        15,
        10100,
        10700
      ],
      [
        15,
        16,
        10710,
        11130
      ],
      [
        16,
        17,
        11140,
        12600
      ]
    ],
    "url": "Shuraym/mp3/025008.mp3",
    "verse": 8
  },
  {
    "chapter": 25,
    "segments": [
      [
        0,
        1,
        70,
        920
      ],
      [
        1,
        2,
        930,
        1410
      ],
      [
        2,
        3,
        1420,
        2160
      ],
      [
        3,
        4,
        2170,
        2490
      ],
      [
        4,
        5,
        2500,
        3410
      ],
      [
        5,
        6,
        3420,
        4370
      ],
      [
        6,
        7,
        4380,
        4920
      ],
      [
        7,
        8,
        4930,
        6280
      ],
      [
        8,
        9,
        6290,
        7110
      ]
    ],
    "url": "Shuraym/mp3/025009.mp3",
    "verse": 9
  },
  {
    "chapter": 25,
    "segments": [
      [
        0,
        1,
        50,
        700
      ],
      [
        1,
        2,
        710,
        1580
      ],
      [
        2,
        3,
        1590,
        1890
      ],
      [
        3,
        4,
        1900,
        3090
      ],
      [
        4,
        5,
        3100,
        3670
      ],
      [
        5,
        6,
        3680,
        3850
      ],
      [
        6,
        7,
        3860,
        4350
      ],
      [
        7,
        8,
        4360,
        5160
      ],
      [
        8,
        9,
        5170,
        5800
      ],
      [
        9,
        10,
        5810,
        7120
      ],
      [
        10,
        11,
        7130,
        7720
      ],
      [
        11,
        12,
        7730,
        8260
      ],
      [
        12,
        13,
        8270,
        8830
      ],
      [
        13,
        14,
        8840,
        9670
      ],
      [
        14,
        15,
        9680,
        10530
      ],
      [
        15,
        16,
        10540,
        10690
      ],
      [
        16,
        17,
        10700,
        11580
      ]
    ],
    "url": "Shuraym/mp3/025010.mp3",
    "verse": 10
  }
]
