[
  {
    "chapter": 66,
    "segments": [
      [
        0,
        1,
        100,
        1010
      ],
      [
        1,
        2,
        1020,
        2000
      ],
      [
        2,
        3,
        2010,
        2300
      ],
      [
        3,
        4,
        2310,
        3170
      ],
      [
        4,
        5,
        3180,
        3440
      ],
      [
        5,
        6,
        3450,
        4100
      ],
      [
        6,
        7,
        4110,
        4760
      ],
      [
        7,
        8,
        4770,
        5130
      ],
      [
        8,
        9,
        5140,
        5980
      ],
      [
        9,
        10,
        5990,
        6580
      ],
      [
        10,
        11,
        6590,
        7910
      ],
      [
        11,
        12,
        7920,
        8650
      ],
      [
        12,
        13,
        8660,
        9380
      ],
      [
        13,
        14,
        9390,
        10350
      ]
    ],
    "url": "Shuraym/mp3/066001.mp3",
    "verse": 1
  },
  {
    "chapter": 66,
    "segments": [
      [
        0,
        1,
        100,
        310
      ],
      [
        1,
        2,
        320,
        760
      ],
      [
        2,
        3,
        770,
        1390
      ],
      [
        3,
        4,
        1400,
        1820
      ],
      [
        4,
        5,
        1830,
        2620
      ],
      [
        5,
        6,
        2630,
        3760
      ],
      [
        6,
        7,
        3770,
        4500
      ],
      [
        7,
        8,
        4510,
        7470
      ],
      [
        8,
        9,
        7480,
        7970
      ],
      [
        9,
        10,
        7980,
        8720
      ],
      [
        10,
        11,
        8730,
        9690
      ]
    ],
    "url": "Shuraym/mp3/066002.mp3",
    "verse": 2
  },
  {
    "chapter": 66,
    "segments": [
      [
        0,
        1,
        50,
        420
      ],
      [
        1,
        2,
        430,
        1020
      ],
      [
        2,
        3,
        1030,
        1910
      ],
      [
        3,
        4,
        1920,
        2320
      ],
      [
        4,
        5,
        2330,
        2790
      ],
      [
        5,
        6,
        2800,
        3810
      ],
      [
        6,
        7,
        3820,
        5060
      ],
      [
        7,
        8,
        5070,
        5990
      ],
      [
        8,
        9,
        6000,
        6690
      ],
      [
        9,
        10,
        6700,
        7150
      ],
      [
        10,
        11,
        7160,
        8100
      ],
      [
        11,
        12,
        8110,
        8620
      ],
      [
        12,
        13,
        8630,
        9220
      ],
      [
        13,
        14,
        9230,
        9830
      ],
      [
        14,
        15,
        9840,
        10600
      ],
      [
        15,
        16,
        10610,
        11330
      ],
      [
        16,
        17,
        11340,
        11940
      ],
      [
        17,
        18,
        11950,
        12640
      ],
      [
        18,
        19,
        12650,
        13470
      ],
      [
        19,
        20,
        13480,
        14330
      ],
      [
        20,
        21,
        14340,
        14790
      ],
      [
        21,
        22,
        14800,
        15410
      ],
      [
        22,
        23,
        15420,
        15710
      ],
      [
        23,
        24,
        15720,
        17020
      ],
      [
        24,
        25,
        17030,
        18030
      ],
      [
        25,
        26,
        18040,
        18480
      ],
      [
        26,
        27,
        18490,
        19370
      ],
      [
        27,
        28,
        19380,
        20090
      ],
      [
        28,
        29,
        20100,
        21160
      ]
    ],
    "url": "Shuraym/mp3/066003.mp3",
    "verse": 3
  },
  {
    "chapter": 66,
    "segments": [
      [
        0,
        1,
        40,
        450
      ],
      [
        1,
        2,
        460,
        1480
      ],
      [
        2,
        3,
        1490,
        1750
      ],
      [
        3,
        4,
        1760,
        2400
      ],
      [
        4,
        5,
        2410,
        2920
      ],
      [
        5,
        6,
        2930,
        3470
      ],
      [
        6,
        7,
        3480,
        5000
      ],
      [
        7,
        8,
        5010,
        5640
      ],
      [
        8,
        9,
        5650,
        6550
      ],
      [
        9,
        10,
        6560,
        7150
      ],
      [
        10,
        11,
        7160,
        8000
      ],
      [
        11,
        12,
        8010,
        8620
      ],
      [
        12,
        13,
        8630,
        8950
      ],
      [
        13,
        14,
        8960,
        9690
      ],
      [
        14,
        15,
        9700,
        10630
      ],
      [
        15,
        16,
        10640,
        11430
      ],
      [
        16,
        17,
        11440,
        14610
      ],
      [
        17,
        18,
        14620,
        16680
      ],
      [
        18,
        19,
        16690,
        17150
      ],
      [
        19,
        20,
        17160,
        17860
      ],
      [
        20,
        21,
        17870,
        18840
      ]
    ],
    "url": "Shuraym/mp3/066004.mp3",
    "verse": 4
  },
  {
    "chapter": 66,
    "segments": [
      [
        0,
        1,
        400,
        750
      ],
      [
        1,
        2,
        760,
        1520
      ],
      [
        2,
        3,
        1530,
        1970
      ],
      [
        3,
        4,
        1980,
        3110
      ],
      [
        4,
        5,
        3120,
        3730
      ],
      [
        5,
        6,
        3740,
        4440
      ],
      [
        6,
        7,
        4450,
        5220
      ],
      [
        7,
        8,
        5230,
        5590
      ],
      [
        8,
        9,
        5600,
        7090
      ],
      [
        9,
        10,
        7100,
        8330
      ],
      [
        10,
        11,
        8340,
        9260
      ],
      [
        11,
        12,
        9270,
        10490
      ],
      [
        12,
        13,
        10500,
        11920
      ],
      [
        13,
        14,
        11930,
        16460
      ],
      [
        14,
        15,
        16470,
        18840
      ],
      [
        15,
        16,
        18850,
        20300
      ],
      [
        16,
        17,
        20310,
        21470
      ]
    ],
    "url": "Shuraym/mp3/066005.mp3",
    "verse": 5
  },
  {
    "chapter": 66,
    "segments": [
      [
        0,
        1,
        970,
        1810
      ],
      [
        1,
        2,
        1820,
        2540
      ],
      [
        2,
        3,
        2550,
        3230
      ],
      [
        3,
        4,
        3240,
        3580
      ],
      [
        4,
        5,
        3590,
        4640
      ],
      [
        5,
        6,
        4650,
        5710
      ],
      [
        6,
        7,
        5720,
        6150
      ],
      [
        7,
        8,
        6160,
        7260
      ],
      [
        8,
        9,
        7270,
        7980
      ],
      [
        9,
        10,
        7990,
        9360
      ],
      [
        10,
        11,
        9370,
        10030
      ],
      [
        11,
        12,
        10040,
        11730
      ],
      [
        12,
        13,
        11740,
        12980
      ],
      [
        13,
        14,
        12990,
        13690
      ],
      [
        14,
        15,
        13700,
        14060
      ],
      [
        15,
        16,
        14070,
        14870
      ],
      [
        16,
        17,
        14880,
        15490
      ],
      [
        17,
        18,
        15500,
        15780
      ],
      [
        18,
        19,
        15790,
        19780
      ],
      [
        19,
        20,
        19790,
        20830
      ],
      [
        20,
        21,
        20840,
        21080
      ],
      [
        21,
        22,
        21090,
        22130
      ]
    ],
    "url": "Shuraym/mp3/066006.mp3",
    "verse": 6
  },
  {
    "chapter": 66,
    "segments": [
      [
        0,
        1,
        280,
        1320
      ],
      [
        1,
        2,
        1330,
        2020
      ],
      [
        2,
        3,
        2030,
        2660
      ],
      [
        3,
        4,
        2670,
        2910
      ],
      [
        4,
        5,
        2920,
        3690
      ],
      [
        5,
        6,
        3700,
        4580
      ],
      [
        6,
        7,
        4590,
        5380
      ],
      [
        7,
        8,
        5390,
        6140
      ],
      [
        8,
        9,
        6150,
        6350
      ],
      [
        9,
        10,
        6360,
        7280
      ],
      [
        10,
        11,
        7290,
        8450
      ]
    ],
    "url": "Shuraym/mp3/066007.mp3",
    "verse": 7
  },
  {
    "chapter": 66,
    "segments": [
      [
        0,
        1,
        60,
        930
      ],
      [
        1,
        2,
        940,
        1650
      ],
      [
        2,
        3,
        1660,
        2390
      ],
      [
        3,
        4,
        2400,
        3330
      ],
      [
        4,
        5,
        3340,
        3650
      ],
      [
        5,
        6,
        3660,
        4400
      ],
      [
        6,
        7,
        4410,
        5160
      ],
      [
        7,
        8,
        5170,
        6910
      ],
      [
        8,
        9,
        6920,
        7270
      ],
      [
        9,
        10,
        7280,
        8070
      ],
      [
        10,
        11,
        8080,
        8600
      ],
      [
        11,
        12,
        8610,
        9250
      ],
      [
        12,
        13,
        9260,
        10070
      ],
      [
        13,
        14,
        10080,
        11290
      ],
      [
        14,
        15,
        11300,
        12320
      ],
      [
        15,
        16,
        12330,
        13600
      ],
      [
        16,
        17,
        13610,
        14230
      ],
      [
        17,
        18,
        14240,
        14670
      ],
      [
        18,
        19,
        14680,
        15260
      ],
      [
        19,
        20,
        15270,
        21580
      ],
      [
        20,
        21,
        21590,
        22070
      ],
      [
        21,
        22,
        22080,
        22310
      ],
      [
        22,
        23,
        22320,
        22800
      ],
      [
        23,
        24,
        22810,
        23340
      ],
      [
        24,
        25,
        23350,
        24210
      ],
      [
        25,
        26,
        24220,
        25050
      ],
      [
        26,
        27,
        25060,
        25840
      ],
      [
        27,
        28,
        25850,
        26670
      ],
      [
        28,
        29,
        26680,
        27370
      ],
      [
        29,
        30,
        27380,
        27940
      ],
      [
        30,
        31,
        27950,
        28380
      ],
      [
        31,
        32,
        28390,
        29290
      ],
      [
        32,
        33,
        29300,
        31060
      ],
      [
        33,
        34,
        31070,
        31940
      ],
      [
        34,
        35,
        31950,
        32680
      ],
      [
        35,
        36,
        32690,
        33270
      ],
      [
        36,
        37,
        33280,
        33870
      ],
      [
        37,
        38,
        33880,
        34630
      ],
      [
        38,
        39,
        34640,
        35240
      ],
      [
        39,
        40,
        35250,
        36260
      ],
      [
        40,
        41,
        36270,
        37180
      ],
      [
        41,
        42,
        37190,
        37770
      ],
      [
        42,
        43,
        37780,
        38340
      ],
      [
        43,
        44,
        38350,
        39450
      ],
      [
        44,
        45,
        39460,
        41130
      ]
    ],
    "url": "Shuraym/mp3/066008.mp3",
    "verse": 8
  },
  {
    "chapter": 66,
    "segments": [
      [
        0,
        1,
        40,
        930
      ],
      [
        1,
        2,
        940,
        1820
      ],
      [
        2,
        3,
        1830,
        2470
      ],
      [
        3,
        4,
        2480,
        3370
      ],
      [
        4,
        5,
        3380,
        4780
      ],
      [
        5,
        6,
        4790,
        5360
      ],
      [
        6,
        7,
        5370,
        6460
      ],
      [
        7,
        8,
        6470,
        7470
      ],
      [
        8,
        9,
        7480,
        8500
      ],
      [
        9,
        10,
        8510,
        9090
      ],
      [
        10,
        11,
        9100,
        10290
      ]
    ],
    "url": "Shuraym/mp3/066009.mp3",
    "verse": 9
  },
  {
    "chapter": 66,
    "segments": [
      [
        0,
        1,
        100,
        480
      ],
      [
        1,
        2,
        490,
        1110
      ],
      [
        2,
        3,
        1120,
        1460
      ],
      [
        3,
        4,
        1470,
        2530
      ],
      [
        4,
        5,
        2540,
        3060
      ],
      [
        5,
        6,
        3070,
        3640
      ],
      [
        6,
        7,
        3650,
        4460
      ],
      [
        7,
        8,
        4470,
        5230
      ],
      [
        8,
        9,
        5240,
        6420
      ],
      [
        9,
        10,
        6430,
        7170
      ],
      [
        10,
        11,
        7180,
        7610
      ],
      [
        11,
        12,
        7620,
        8390
      ],
      [
        12,
        13,
        8400,
        8630
      ],
      [
        13,
        14,
        8640,
        9480
      ],
      [
        14,
        15,
        9490,
        10520
      ],
      [
        15,
        16,
        10530,
        13800
      ],
      [
        16,
        17,
        13810,
        14250
      ],
      [
        17,
        18,
        14260,
        14960
      ],
      [
        18,
        19,
        14970,
        15750
      ],
      [
        19,
        20,
        15760,
        16020
      ],
      [
        20,
        21,
        16030,
        16650
      ],
      [
        21,
        22,
        16660,
        17110
      ],
      [
        22,
        23,
        17120,
        18090
      ],
      [
        23,
        24,
        18100,
        18610
      ],
      [
        24,
        25,
        18620,
        19360
      ],
      [
        25,
        26,
        19370,
        19650
      ],
      [
        26,
        27,
        19660,
        21030
      ]
    ],
    "url": "Shuraym/mp3/066010.mp3",
    "verse": 10
  }
]
