[
  {
    "chapter": 40,
    "segments": [
      [
        0,
        1,
        0,
        3700
      ]
    ],
    "url": "//mirrors.quranicaudio.com/everyayah/Husary_Muallim_128kbps/040001.mp3",
    "verse": 1
  },
  {
    "chapter": 40,
    "segments": [
      [
        0,
        1,
        250,
        1880
      ],
      [
        1,
        2,
        1890,
        3240
      ],
      [
        2,
        3,
        3250,
        3670
      ],
      [
        3,
        4,
        3680,
        4880
      ],
      [
        4,
        5,
        4890,
        6250
      ],
      [
        5,
        6,
        6260,
        7590
      ]
    ],
    "url": "//mirrors.quranicaudio.com/everyayah/Husary_Muallim_128kbps/040002.mp3",
    "verse": 2
  },
  {
    "chapter": 40,
    "segments": [
      [
        0,
        1,
        300,
        1360
      ],
      [
        1,
        2,
        1370,
        2880
      ],
      [
        2,
        3,
        2890,
        4280
      ],
      [
        3,
        4,
        4290,
        5240
      ],
      [
        4,
        5,
        5250,
        6430
      ],
      [
        5,
        6,
        6440,
        7800
      ],
      [
        6,
        7,
        7810,
        8010
      ],
      [
        7,
        8,
        8020,
        13420
      ],
      [
        8,
        9,
        13430,
        15010
      ],
      [
        9,
        10,
        15020,
        16130
      ],
      [
        10,
        11,
        16140,
        17340
      ],
      [
        11,
        12,
        17350,
        18100
      ],
      [
        12,
        13,
        21750,
        22570
      ],
      [
        13,
        14,
        22580,
        24210
      ]
    ],
    "url": "//mirrors.quranicaudio.com/everyayah/Husary_Muallim_128kbps/040003.mp3",
    "verse": 3
  },
  {
    "chapter": 40,
    "segments": [
      [
        0,
        1,
        400,
        820
      ],
      [
        1,
        2,
        830,
        2210
      ],
      [
        2,
        3,
        2220,
        3650
      ],
      [
        3,
        4,
        3660,
        5230
      ],
      [
        4,
        5,
        5240,
        6300
      ],
      [
        5,
        6,
        6310,
        7010
      ],
      [
        6,
        7,
        7020,
        8350
      ],
      [
        7,
        8,
        8360,
        9550
      ],
      [
        8,
        9,
        14200,
        14760
      ],
      [
        9,
        10,
        14770,
        16060
      ],
      [
        10,
        11,
        16070,
        18030
      ],
      [
        11,
        12,
        18040,
        18360
      ],
      [
        12,
        13,
        18370,
        19760
      ]
    ],
    "url": "//mirrors.quranicaudio.com/everyayah/Husary_Muallim_128kbps/040004.mp3",
    "verse": 4
  },
  {
    "chapter": 40,
    "segments": [
      [
        0,
        1,
        350,
        1460
      ],
      [
        1,
        2,
        1470,
        2860
      ],
      [
        2,
        3,
        2870,
        3700
      ],
      [
        3,
        4,
        3710,
        5200
      ],
      [
        4,
        5,
        5210,
        7060
      ],
      [
        5,
        6,
        7070,
        8020
      ],
      [
        6,
        7,
        8030,
        9400
      ],
      [
        7,
        8,
        12700,
        14140
      ],
      [
        8,
        9,
        14150,
        14940
      ],
      [
        9,
        10,
        14950,
        17120
      ],
      [
        10,
        11,
        17130,
        18940
      ],
      [
        11,
        12,
        18950,
        20900
      ],
      [
        12,
        13,
        25200,
        26650
      ],
      [
        13,
        14,
        26660,
        28280
      ],
      [
        14,
        15,
        28290,
        29870
      ],
      [
        15,
        16,
        29880,
        30420
      ],
      [
        16,
        17,
        30430,
        31480
      ],
      [
        17,
        18,
        31490,
        33550
      ],
      [
        18,
        19,
        38350,
        39030
      ],
      [
        19,
        20,
        39040,
        39910
      ],
      [
        20,
        21,
        39920,
        41270
      ]
    ],
    "url": "//mirrors.quranicaudio.com/everyayah/Husary_Muallim_128kbps/040005.mp3",
    "verse": 5
  },
  {
    "chapter": 40,
    "segments": [
      [
        0,
        1,
        200,
        1680
      ],
      [
        1,
        2,
        1690,
        2870
      ],
      [
        2,
        3,
        2880,
        3940
      ],
      [
        3,
        4,
        3950,
        4970
      ],
      [
        4,
        5,
        4980,
        5460
      ],
      [
        5,
        6,
        5470,
        6870
      ],
      [
        6,
        7,
        6880,
        8980
      ],
      [
        7,
        8,
        8990,
        10660
      ],
      [
        8,
        9,
        10670,
        12170
      ],
      [
        9,
        10,
        12180,
        14040
      ]
    ],
    "url": "//mirrors.quranicaudio.com/everyayah/Husary_Muallim_128kbps/040006.mp3",
    "verse": 6
  },
  {
    "chapter": 40,
    "segments": [
      [
        0,
        1,
        50,
        1540
      ],
      [
        1,
        2,
        1550,
        3130
      ],
      [
        2,
        3,
        3140,
        4200
      ],
      [
        3,
        4,
        4210,
        5040
      ],
      [
        4,
        5,
        5050,
        6510
      ],
      [
        5,
        6,
        6520,
        8750
      ],
      [
        6,
        7,
        13980,
        14960
      ],
      [
        7,
        8,
        14970,
        16460
      ],
      [
        8,
        9,
        16470,
        18370
      ],
      [
        9,
        10,
        18380,
        19250
      ],
      [
        10,
        11,
        19260,
        21830
      ],
      [
        11,
        12,
        21840,
        23440
      ],
      [
        12,
        13,
        23450,
        24950
      ],
      [
        13,
        14,
        29700,
        30750
      ],
      [
        14,
        15,
        30760,
        31870
      ],
      [
        15,
        16,
        31880,
        32710
      ],
      [
        16,
        17,
        32720,
        33570
      ],
      [
        17,
        18,
        33580,
        35760
      ],
      [
        18,
        19,
        35770,
        37440
      ],
      [
        19,
        20,
        37450,
        38440
      ],
      [
        20,
        21,
        38450,
        40250
      ],
      [
        21,
        22,
        40260,
        41550
      ],
      [
        22,
        23,
        49860,
        51430
      ],
      [
        23,
        24,
        51440,
        52880
      ],
      [
        24,
        25,
        52890,
        53900
      ],
      [
        25,
        26,
        53910,
        55030
      ],
      [
        26,
        27,
        55040,
        56500
      ]
    ],
    "url": "//mirrors.quranicaudio.com/everyayah/Husary_Muallim_128kbps/040007.mp3",
    "verse": 7
  },
  {
    "chapter": 40,
    "segments": [
      [
        0,
        1,
        150,
        1320
      ],
      [
        1,
        2,
        1330,
        3230
      ],
      [
        2,
        3,
        3240,
        4900
      ],
      [
        3,
        4,
        4910,
        5960
      ],
      [
        4,
        5,
        5970,
        7140
      ],
      [
        5,
        6,
        7150,
        8830
      ],
      [
        6,
        7,
        8840,
        10060
      ],
      [
        7,
        8,
        10070,
        11000
      ],
      [
        8,
        9,
        16780,
        17380
      ],
      [
        9,
        10,
        17390,
        20350
      ],
      [
        10,
        11,
        20360,
        22630
      ],
      [
        11,
        12,
        22640,
        25600
      ],
      [
        12,
        13,
        29900,
        31240
      ],
      [
        13,
        14,
        31250,
        32520
      ],
      [
        14,
        15,
        32530,
        33970
      ],
      [
        15,
        16,
        33980,
        35420
      ]
    ],
    "url": "//mirrors.quranicaudio.com/everyayah/Husary_Muallim_128kbps/040008.mp3",
    "verse": 8
  },
  {
    "chapter": 40,
    "segments": [
      [
        0,
        1,
        250,
        1160
      ],
      [
        1,
        2,
        1170,
        3500
      ],
      [
        2,
        3,
        7550,
        8590
      ],
      [
        3,
        4,
        8600,
        9140
      ],
      [
        4,
        5,
        9150,
        11120
      ],
      [
        5,
        6,
        11130,
        13110
      ],
      [
        6,
        7,
        13120,
        13860
      ],
      [
        7,
        8,
        13870,
        15400
      ],
      [
        8,
        9,
        20550,
        21700
      ],
      [
        9,
        10,
        21710,
        22270
      ],
      [
        10,
        11,
        22280,
        23490
      ],
      [
        11,
        12,
        23500,
        25190
      ]
    ],
    "url": "//mirrors.quranicaudio.com/everyayah/Husary_Muallim_128kbps/040009.mp3",
    "verse": 9
  },
  {
    "chapter": 40,
    "segments": [
      [
        0,
        1,
        350,
        1460
      ],
      [
        1,
        2,
        1470,
        2770
      ],
      [
        2,
        3,
        2780,
        3960
      ],
      [
        3,
        4,
        3970,
        5590
      ],
      [
        4,
        5,
        5600,
        6630
      ],
      [
        5,
        6,
        6640,
        7790
      ],
      [
        6,
        7,
        7800,
        8840
      ],
      [
        7,
        8,
        8850,
        9800
      ],
      [
        8,
        9,
        9810,
        11190
      ],
      [
        9,
        10,
        11200,
        13450
      ],
      [
        10,
        11,
        13460,
        13860
      ],
      [
        11,
        12,
        13870,
        15650
      ],
      [
        12,
        13,
        22070,
        22550
      ],
      [
        13,
        14,
        22560,
        24290
      ],
      [
        14,
        15,
        24300,
        26430
      ]
    ],
    "url": "//mirrors.quranicaudio.com/everyayah/Husary_Muallim_128kbps/040010.mp3",
    "verse": 10
  }
]
