[
  {
    "chapter": 8,
    "segments": [
      [
        0,
        1,
        200,
        2340
      ],
      [
        1,
        2,
        2350,
        2950
      ],
      [
        2,
        3,
        2960,
        5400
      ],
      [
        3,
        4,
        9550,
        9950
      ],
      [
        4,
        5,
        9960,
        12470
      ],
      [
        5,
        6,
        12480,
        14220
      ],
      [
        6,
        7,
        14230,
        16250
      ],
      [
        7,
        8,
        21000,
        22080
      ],
      [
        8,
        9,
        22090,
        23430
      ],
      [
        9,
        10,
        23440,
        25430
      ],
      [
        10,
        11,
        25440,
        26470
      ],
      [
        11,
        12,
        26480,
        28150
      ],
      [
        12,
        13,
        28160,
        29880
      ],
      [
        13,
        14,
        29890,
        31240
      ],
      [
        14,
        15,
        31250,
        33200
      ],
      [
        15,
        16,
        45770,
        46950
      ],
      [
        16,
        17,
        46960,
        49350
      ],
      [
        17,
        18,
        49360,
        50560
      ]
    ],
    "url": "//mirrors.quranicaudio.com/everyayah/Husary_Muallim_128kbps/008001.mp3",
    "verse": 1
  },
  {
    "chapter": 8,
    "segments": [
      [
        0,
        1,
        350,
        1840
      ],
      [
        1,
        2,
        1850,
        4140
      ],
      [
        2,
        3,
        4150,
        5760
      ],
      [
        3,
        4,
        5770,
        6810
      ],
      [
        4,
        5,
        6820,
        8070
      ],
      [
        5,
        6,
        8080,
        9310
      ],
      [
        6,
        7,
        9320,
        10550
      ],
      [
        7,
        8,
        10560,
        12500
      ],
      [
        8,
        9,
        25410,
        26760
      ],
      [
        9,
        10,
        26770,
        28100
      ],
      [
        10,
        11,
        28250,
        29970
      ],
      [
        11,
        12,
        29980,
        32570
      ],
      [
        12,
        13,
        32580,
        34760
      ],
      [
        13,
        14,
        34770,
        37000
      ],
      [
        14,
        15,
        54860,
        56240
      ],
      [
        15,
        16,
        56250,
        57850
      ],
      [
        16,
        17,
        57860,
        60580
      ]
    ],
    "url": "//mirrors.quranicaudio.com/everyayah/Husary_Muallim_128kbps/008002.mp3",
    "verse": 2
  },
  {
    "chapter": 8,
    "segments": [
      [
        0,
        1,
        250,
        2010
      ],
      [
        1,
        2,
        2020,
        4030
      ],
      [
        2,
        3,
        4040,
        5760
      ],
      [
        3,
        4,
        5770,
        7750
      ],
      [
        4,
        5,
        7760,
        10150
      ],
      [
        5,
        6,
        10160,
        12600
      ]
    ],
    "url": "//mirrors.quranicaudio.com/everyayah/Husary_Muallim_128kbps/008003.mp3",
    "verse": 3
  },
  {
    "chapter": 8,
    "segments": [
      [
        0,
        1,
        200,
        2770
      ],
      [
        1,
        2,
        2780,
        3440
      ],
      [
        2,
        3,
        3450,
        5590
      ],
      [
        3,
        4,
        5600,
        7300
      ],
      [
        4,
        5,
        11800,
        12520
      ],
      [
        5,
        6,
        12530,
        14470
      ],
      [
        6,
        7,
        14480,
        15780
      ],
      [
        7,
        8,
        15790,
        17500
      ],
      [
        8,
        9,
        17510,
        20180
      ],
      [
        9,
        10,
        20190,
        22300
      ],
      [
        10,
        11,
        22310,
        23660
      ]
    ],
    "url": "//mirrors.quranicaudio.com/everyayah/Husary_Muallim_128kbps/008004.mp3",
    "verse": 4
  },
  {
    "chapter": 8,
    "segments": [
      [
        0,
        1,
        350,
        2330
      ],
      [
        1,
        2,
        2340,
        3890
      ],
      [
        2,
        3,
        3900,
        5330
      ],
      [
        3,
        4,
        5340,
        6390
      ],
      [
        4,
        5,
        6400,
        7770
      ],
      [
        5,
        6,
        7780,
        9470
      ],
      [
        6,
        7,
        9480,
        11220
      ],
      [
        7,
        8,
        11230,
        21320
      ],
      [
        8,
        9,
        21330,
        21750
      ],
      [
        9,
        10,
        21760,
        24030
      ],
      [
        10,
        11,
        24040,
        26420
      ]
    ],
    "url": "//mirrors.quranicaudio.com/everyayah/Husary_Muallim_128kbps/008005.mp3",
    "verse": 5
  },
  {
    "chapter": 8,
    "segments": [
      [
        0,
        1,
        450,
        2840
      ],
      [
        1,
        2,
        2850,
        3190
      ],
      [
        2,
        3,
        3200,
        4490
      ],
      [
        3,
        4,
        4500,
        6170
      ],
      [
        4,
        5,
        6180,
        7740
      ],
      [
        5,
        6,
        7750,
        10130
      ],
      [
        6,
        7,
        10140,
        12170
      ],
      [
        7,
        8,
        12180,
        12760
      ],
      [
        8,
        9,
        12770,
        14160
      ],
      [
        9,
        10,
        14170,
        15100
      ],
      [
        10,
        11,
        15110,
        17720
      ]
    ],
    "url": "//mirrors.quranicaudio.com/everyayah/Husary_Muallim_128kbps/008006.mp3",
    "verse": 6
  },
  {
    "chapter": 8,
    "segments": [
      [
        0,
        1,
        300,
        1140
      ],
      [
        1,
        2,
        1150,
        2750
      ],
      [
        2,
        3,
        2760,
        4160
      ],
      [
        3,
        4,
        4170,
        5080
      ],
      [
        4,
        5,
        5090,
        9050
      ],
      [
        5,
        6,
        9060,
        10960
      ],
      [
        6,
        7,
        10970,
        11970
      ],
      [
        7,
        8,
        11980,
        14350
      ],
      [
        8,
        9,
        20260,
        21500
      ],
      [
        9,
        10,
        21510,
        22560
      ],
      [
        10,
        11,
        22570,
        23520
      ],
      [
        11,
        12,
        23530,
        25240
      ],
      [
        12,
        13,
        25250,
        26660
      ],
      [
        13,
        14,
        26670,
        27640
      ],
      [
        14,
        15,
        27650,
        29390
      ],
      [
        15,
        16,
        29400,
        30850
      ],
      [
        16,
        17,
        37300,
        38430
      ],
      [
        17,
        18,
        38440,
        39690
      ],
      [
        18,
        19,
        39700,
        41090
      ],
      [
        19,
        20,
        41100,
        43850
      ],
      [
        20,
        21,
        43860,
        45440
      ],
      [
        21,
        22,
        45450,
        46780
      ],
      [
        22,
        23,
        46790,
        49220
      ]
    ],
    "url": "//mirrors.quranicaudio.com/everyayah/Husary_Muallim_128kbps/008007.mp3",
    "verse": 7
  },
  {
    "chapter": 8,
    "segments": [
      [
        0,
        1,
        350,
        1790
      ],
      [
        1,
        2,
        1800,
        3140
      ],
      [
        2,
        3,
        3150,
        4680
      ],
      [
        3,
        4,
        4690,
        6340
      ],
      [
        4,
        5,
        6350,
        7240
      ],
      [
        5,
        6,
        7250,
        8230
      ],
      [
        6,
        7,
        8240,
        10650
      ]
    ],
    "url": "//mirrors.quranicaudio.com/everyayah/Husary_Muallim_128kbps/008008.mp3",
    "verse": 8
  },
  {
    "chapter": 8,
    "segments": [
      [
        0,
        1,
        350,
        660
      ],
      [
        1,
        2,
        670,
        3460
      ],
      [
        2,
        3,
        3470,
        5210
      ],
      [
        3,
        4,
        5220,
        7230
      ],
      [
        4,
        5,
        7240,
        8100
      ],
      [
        5,
        6,
        14750,
        16530
      ],
      [
        6,
        7,
        16540,
        18840
      ],
      [
        7,
        8,
        18850,
        21030
      ],
      [
        8,
        9,
        21040,
        21510
      ],
      [
        9,
        10,
        21520,
        24950
      ],
      [
        10,
        11,
        24960,
        26990
      ]
    ],
    "url": "//mirrors.quranicaudio.com/everyayah/Husary_Muallim_128kbps/008009.mp3",
    "verse": 9
  },
  {
    "chapter": 8,
    "segments": [
      [
        0,
        1,
        250,
        1070
      ],
      [
        1,
        2,
        1080,
        2360
      ],
      [
        2,
        3,
        2370,
        3720
      ],
      [
        3,
        4,
        3730,
        5140
      ],
      [
        4,
        5,
        5150,
        6590
      ],
      [
        5,
        6,
        6600,
        9470
      ],
      [
        6,
        7,
        9480,
        10450
      ],
      [
        7,
        8,
        10460,
        12450
      ],
      [
        8,
        9,
        16550,
        17050
      ],
      [
        9,
        10,
        17060,
        18750
      ],
      [
        10,
        11,
        18760,
        20110
      ],
      [
        11,
        12,
        20120,
        20700
      ],
      [
        12,
        13,
        20710,
        22130
      ],
      [
        13,
        14,
        22140,
        23450
      ],
      [
        14,
        15,
        27750,
        29010
      ],
      [
        15,
        16,
        29020,
        30320
      ],
      [
        16,
        17,
        30330,
        32120
      ],
      [
        17,
        18,
        32130,
        33810
      ]
    ],
    "url": "//mirrors.quranicaudio.com/everyayah/Husary_Muallim_128kbps/008010.mp3",
    "verse": 10
  }
]
